array_record_beam_sdk/__init__.py
array_record_beam_sdk/arrayrecordio.py
array_record_beam_sdk/demo.py
array_record_beam_sdk/dofns.py
array_record_beam_sdk/example.py
array_record_beam_sdk/options.py
array_record_beam_sdk/pipelines.py
array_record_beam_sdk/testdata.py
array_record_beam_sdk/examples/example_full_demo_cli.sh
array_record_beam_sdk/examples/example_gcs_conversion.py
array_record_beam_sdk/examples/example_sink_conversion.py
array_record_beam_sdk-0.1.0.dist-info/LICENSE
array_record_beam_sdk-0.1.0.dist-info/METADATA
array_record_beam_sdk-0.1.0.dist-info/WHEEL
array_record_beam_sdk-0.1.0.dist-info/top_level.txt
array_record_beam_sdk-0.1.0.dist-info/RECORD
