Metadata-Version: 2.1
Name: array_record_beam_sdk
Version: 0.1.0
Summary: A set of Beam pipelines for converting TFRecord to Array Record
Author: Rob Hilton
License: Apache License
License-File: LICENSE
Requires-Dist: apache-beam[gcp] >=2.50.0
Requires-Dist: google-cloud-storage >=2.11.0
Requires-Dist: tensorflow >=2.14.0
Requires-Dist: array-record ==0.5.0
